pycounts_ps/__init__.py
pycounts_ps/plotting.py
pycounts_ps/pycounts_ps.py
pycounts_ps-0.1.0.dist-info/LICENSE
pycounts_ps-0.1.0.dist-info/METADATA
pycounts_ps-0.1.0.dist-info/WHEEL
pycounts_ps-0.1.0.dist-info/RECORD
