Metadata-Version: 2.3
Name: pycounts_ps
Version: 0.1.0
Summary: A package for counting number of words in a text file
License: MIT
Author: Paramveer Singh
Requires-Python: >=3.11
Classifier: License :: OSI Approved :: MIT License
Classifier: Programming Language :: Python :: 3
Classifier: Programming Language :: Python :: 3.11
Classifier: Programming Language :: Python :: 3.12
Classifier: Programming Language :: Python :: 3.13
Requires-Dist: matplotlib (>=3.10.0)
